TP1/alu8bits.v
module alu8bit(
  input [7:0] a,
  input [7:0] b,
  input [2:0] opcode,
  output reg [7:0] result,
  output reg [3:0] flags
  // flags[0]: Zero, flags[1]: Carry, flags[2]: Negative, flags[3]: Overflow
);

  reg carry; //bit auxiliar para carry
  reg overflow; //bit auxiliar para overflow

  always @(*) begin
    result = 0;
    carry = 0;
    overflow = 0;

    case (opcode)
      3'b000: begin //suma
      result = a + b;     
      {carry, result} = a + b; // Captura el carry
      overflow = (a[7] == b[7]) && (result[7])!= a[7]; // ALU detecta overflow
      end

      3'b001: begin //resta 
      {carry, result} = a - b; // Captura el carry
      overflow = (a[7] == b[7]) && (result[7])!= a[7]; // ALU detecta overflow
      end

      3'b010: result = a & b;         // AND
      3'b011: result = a | b;      // OR
      3'b100: result= a ^ b;        // XOR

      3'b101: result = (a < b) ? 8'b00000001 : 8'b00000000; 
      // Comparación, si a < b, result = 1, else 0
      
      default: result = 4'b0000;      // Valor por defecto

    endcase

       // Asignación de flags
      flags[0] = (result == 8'b0); // Zero flag
      flags[1] = carry; // Carry flag
      flags[2] = result[7]; // Negative flag
      flags[3] = overflow; // Overflow flag

  end


endmodule

TP1/tb_alu_8bit.v
`timescale 1ns / 1ps
`include "alu8bits.v"

module tb_alu_8bit;
  reg [7:0] a, b;
  reg [2:0] opcode;
  wire [7:0] result;
  wire [3:0] flags;


  alu8bit uut(a, b, opcode, result, flags);

  initial begin
    $dumpfile("alu_8bit.vcd");
    $dumpvars(0, tb_alu_8bit);
  
    opcode = 3'b000; #10; // suma
    opcode = 3'b001; #10; // resta
    opcode = 3'b010; #10; // AND
    opcode = 3'b011; #10; // OR
    opcode = 3'b100; #10; // XOR
    opcode = 3'b101; #10; // comparación


    // Casos de prueba para testeo de flags
    
    a = 8'b00000001; b = 8'b00000001; opcode = 3'b001; #10; 
    // resta que da cero, flag zero
    a = 8'b10000000; b = 8'b00000001; opcode = 3'b000; #10;
    // suma que da overflow, flag overflow
    a = 8'b11111111; b = 8'b00000001; opcode = 3'b000; #10; 
    // suma que da carry, flag carry 

    $finish;
  end
endmodule

TP1/alu_8bit.vcd
$date
	Sun Aug 31 16:38:04 2025
$end
$version
	Icarus Verilog
$end
$timescale
	1ps
$end
$scope module tb_alu_8bit $end
$var wire 8 ! result [7:0] $end
$var wire 4 " flags [3:0] $end
$var reg 8 # a [7:0] $end
$var reg 8 $ b [7:0] $end
$var reg 3 % opcode [2:0] $end
$scope module uut $end
$var wire 8 & a [7:0] $end
$var wire 8 ' b [7:0] $end
$var wire 3 ( opcode [2:0] $end
$var reg 1 ) carry $end
$var reg 4 * flags [3:0] $end
$var reg 1 + overflow $end
$var reg 8 , result [7:0] $end
$upscope $end
$upscope $end
$enddefinitions $end
$comment Show the parameter values. $end
$dumpall
$end
#0
$dumpvars
bx ,
x+
bx *
x)
b0 (
bx '
bx &
b0 %
bx $
bx #
bx "
bx !
$end
#10000
x+
x)
b1 %
b1 (
#20000
b0x0x "
b0x0x *
0+
0)
b10 %
b10 (
#30000
b11 %
b11 (
#40000
b100 %
b100 (
#50000
b0x "
b0x *
b0x !
b0x ,
b101 %
b101 (
#60000
b1 "
b1 *
b0 !
b0 ,
b1 %
b1 (
b1 $
b1 '
b1 #
b1 &
#70000
b100 "
b100 *
b10000001 !
b10000001 ,
b0 %
b0 (
b10000000 #
b10000000 &
#80000
b11 "
b11 *
1)
b0 !
b0 ,
b11111111 #
b11111111 &
